tsp_solutions/__init__.py
tsp_solutions-0.0.2.dist-info/LICENSE.txt
tsp_solutions-0.0.2.dist-info/METADATA
tsp_solutions-0.0.2.dist-info/WHEEL
tsp_solutions-0.0.2.dist-info/top_level.txt
tsp_solutions-0.0.2.dist-info/RECORD
