Metadata-Version: 2.1
Name: tsp-solutions
Version: 0.0.2
Summary: The travelling salesman problem is a np-hard problem with application in supply chain and computer science
Home-page: https://github.com/projektdexter/tsp
Author: Shamik Pushkar
Author-email: shamikpushkar92@gmail.com
Keywords: python,travelling-salesman-problem,combinatorial-optimization,linear-programming,integer-programming,pulp,optimization,heuristics,metaheuristics,vrp,vehicle-routing-problem
License-File: LICENSE.txt
Requires-Dist: numpy
Requires-Dist: pandas
Requires-Dist: pulp
Requires-Dist: scipy
